testmichalk_calc/__init__.py
testmichalk_calc/action/__init__.py
testmichalk_calc/action/mul_action.py
testmichalk_calc/action/sub_action.py
testmichalk_calc/operations.py
testmichalk_calc-0.2.0.dist-info/METADATA
testmichalk_calc-0.2.0.dist-info/WHEEL
testmichalk_calc-0.2.0.dist-info/RECORD
